[
  {
    "ParentTables": {
      "Position": 33,
      "Value": [
        {
          "Position": 37,
          "Value": {
            "Resource": {
              "ObjectName": {
                "String": "AthenaLootTierData_Client"
              },
              "OuterIndex": {
                "Resource": {
                  "ObjectName": {
                    "String": "/Game/Items/Datatables/AthenaLootTierData_Client"
                  },
                  "OuterIndex": {
                    "Resource": null
                  }
                }
              }
            }
          }
        },
        {
          "Position": 41,
          "Value": {
            "Resource": {
              "ObjectName": {
                "String": "AthenaLootTierData_DeimosOverride"
              },
              "OuterIndex": {
                "Resource": {
                  "ObjectName": {
                    "String": "/Game/Athena/Playlists/Deimos/AthenaLootTierData_DeimosOverride"
                  },
                  "OuterIndex": {
                    "Resource": null
                  }
                }
              }
            }
          }
        },
        {
          "Position": 45,
          "Value": {
            "Resource": {
              "ObjectName": {
                "String": "OverrideLootTierData"
              },
              "OuterIndex": {
                "Resource": {
                  "ObjectName": {
                    "String": "/Game/Athena/Playlists/50v50/OverrideLootTierData"
                  },
                  "OuterIndex": {
                    "Resource": null
                  }
                }
              }
            }
          }
        }
      ]
    },
    "RowStruct": {
      "Position": 74,
      "Value": {
        "Resource": {
          "ObjectName": {
            "String": "FortLootTierData"
          },
          "OuterIndex": {
            "Resource": {
              "ObjectName": {
                "String": "/Script/FortniteGame"
              },
              "OuterIndex": {
                "Resource": null
              }
            }
          }
        }
      }
    }
  }
]